perfharness/__init__.py
perfharness/__main__.py
perfharness/argparse_set_ops.py
perfharness/config.py
perfharness/db.py
perfharness/delete.py
perfharness/hash.py
perfharness/machine.py
perfharness/run.py
perfharness/viz.py
perfharness-1.0.3.dist-info/METADATA
perfharness-1.0.3.dist-info/WHEEL
perfharness-1.0.3.dist-info/licenses/LICENSE
perfharness-1.0.3.dist-info/RECORD
