Metadata-Version: 2.4
Name: perfharness
Version: 1.0.3
Summary: Tool for tracking python performance regressions
Project-URL: Repository, https://github.com/rhelmot/perfharness
Author-email: Audrey Dutcher <audrey@rhelmot.io>
License-Expression: MIT
License-File: LICENSE
Keywords: benchmark,performance
Requires-Python: >=3.7
Requires-Dist: distro; sys_platform == 'linux'
Requires-Dist: parsedatetime
Requires-Dist: psutil
Requires-Dist: sqlalchemy
Provides-Extra: viz
Requires-Dist: matplotlib; extra == 'viz'
Requires-Dist: pandas; extra == 'viz'
